traceai_openai/__init__.py
traceai_openai/_attributes/__init__.py
traceai_openai/_attributes/_responses_api.py
traceai_openai/_request.py
traceai_openai/_request_attributes_extractor.py
traceai_openai/_response_accumulator.py
traceai_openai/_response_attributes_extractor.py
traceai_openai/_span_io_handler.py
traceai_openai/_stream.py
traceai_openai/_utils.py
traceai_openai/_with_span.py
traceai_openai/package.py
traceai_openai/py.typed
traceai_openai/version.py
traceai_openai-0.1.9.dist-info/METADATA
traceai_openai-0.1.9.dist-info/WHEEL
traceai_openai-0.1.9.dist-info/RECORD
